webmock/__init__.py
webmock/_version.py
webmock-1.1.0.dist-info/METADATA
webmock-1.1.0.dist-info/top_level.txt
webmock-1.1.0.dist-info/DESCRIPTION.rst
webmock-1.1.0.dist-info/metadata.json
webmock-1.1.0.dist-info/WHEEL
webmock-1.1.0.dist-info/RECORD
