Metadata-Version: 2.0
Name: webmock
Version: 1.1.0
Summary: Mock web server for testing web clients
Home-page: UNKNOWN
Author: Dustin J. Mitchell
Author-email: dustin@v.igoro.us
License: MIT
Keywords: mock testing web http
Platform: UNKNOWN
Classifier: Development Status :: 4 - Beta
Classifier: Intended Audience :: Developers
Classifier: License :: OSI Approved :: MIT License
Classifier: Programming Language :: Python :: 2
Classifier: Programming Language :: Python :: 2.6
Classifier: Programming Language :: Python :: 2.7
Classifier: Programming Language :: Python :: 3
Classifier: Programming Language :: Python :: 3.2
Classifier: Programming Language :: Python :: 3.3
Classifier: Programming Language :: Python :: 3.4
Provides-Extra: test
Requires-Dist: nose; extra == 'test'
Requires-Dist: coverage; extra == 'test'
Requires-Dist: tox; extra == 'test'
